autolingua/__init__.py
autolingua/scripts/cli.py
autolingua/scripts/codification.py
autolingua/scripts/replacement.py
autolingua/utils/__init__.py
autolingua/utils/utils.py
autolingua-0.3.2.dist-info/LICENSE
autolingua-0.3.2.dist-info/METADATA
autolingua-0.3.2.dist-info/WHEEL
autolingua-0.3.2.dist-info/entry_points.txt
autolingua-0.3.2.dist-info/top_level.txt
autolingua-0.3.2.dist-info/RECORD
