Metadata-Version: 2.1
Name: autolingua
Version: 0.3.2
Summary: autolingua description
Author-email: Álvaro Ramajo-Ballester <aramajo@ing.uc3m.es>
Project-URL: Homepage, https://github.com/ramajoballester/autolingua
Project-URL: Bug Tracker, https://github.com/ramajoballester/autolingua/issues
Keywords: python
Classifier: Programming Language :: Python :: 3
Classifier: Programming Language :: Python :: 3.8
Classifier: Programming Language :: Python :: 3.9
Classifier: Programming Language :: Python :: 3.10
Classifier: Programming Language :: Python :: 3.11
Classifier: Programming Language :: Python :: 3.12
Classifier: License :: OSI Approved :: GNU Affero General Public License v3
Classifier: Natural Language :: English
Classifier: Operating System :: POSIX :: Linux
Classifier: Operating System :: MacOS :: MacOS X
Classifier: Operating System :: Microsoft :: Windows
Requires-Python: >=3.8
License-File: LICENSE
Requires-Dist: verbecc
Requires-Dist: pandas
Requires-Dist: numpy
Requires-Dist: openpyxl
Requires-Dist: argparse
Requires-Dist: ipykernel
Requires-Dist: ipywidgets
Requires-Dist: matplotlib
Requires-Dist: seaborn
Provides-Extra: dev
Requires-Dist: ipykernel ; extra == 'dev'
Requires-Dist: ipywidgets ; extra == 'dev'
Requires-Dist: twine ; extra == 'dev'
Requires-Dist: build ; extra == 'dev'
Requires-Dist: bump-my-version ; extra == 'dev'
Provides-Extra: docs
Requires-Dist: sphinx ==7.1.2 ; extra == 'docs'
Requires-Dist: sphinx-rtd-theme ==1.3.0 ; extra == 'docs'
Requires-Dist: sphinx-copybutton ==0.5.1 ; extra == 'docs'
Requires-Dist: sphinx-markdown-tables ==0.0.17 ; extra == 'docs'
Requires-Dist: sphinx-tabs ; extra == 'docs'
Requires-Dist: numpydoc ==1.5.0 ; extra == 'docs'
Requires-Dist: myst-parser ==2.0.0 ; extra == 'docs'
Provides-Extra: full
Requires-Dist: autolingua[dev,docs] ; extra == 'full'
